derailed/__init__.py
derailed/enums.py
derailed/errors.py
derailed/gateway.py
derailed/http.py
derailed/types/guild.py
derailed/types/presence.py
derailed/types/relationship.py
derailed/types/role.py
derailed/types/track.py
derailed/types/user.py
derailed/utils.py
derailed-0.1.0.dist-info/LICENSE
derailed-0.1.0.dist-info/WHEEL
derailed-0.1.0.dist-info/METADATA
derailed-0.1.0.dist-info/RECORD
